django_simple_queue/__init__.py
django_simple_queue/admin.py
django_simple_queue/apps.py
django_simple_queue/models.py
django_simple_queue/tests.py
django_simple_queue/urls.py
django_simple_queue/utils.py
django_simple_queue/views.py
django_simple_queue/management/__init__.py
django_simple_queue/management/commands/task_worker.py
django_simple_queue/migrations/0001_initial.py
django_simple_queue/migrations/__init__.py
django_simple_queue-0.1.10.dist-info/LICENSE
django_simple_queue-0.1.10.dist-info/METADATA
django_simple_queue-0.1.10.dist-info/WHEEL
django_simple_queue-0.1.10.dist-info/top_level.txt
django_simple_queue-0.1.10.dist-info/RECORD
