Metadata-Version: 2.1
Name: django-simple-queue
Version: 0.1.10
Summary: Django based app for Task queue manager using database as the broker.
Home-page: https://github.com/shubhamdipt/django-simple-queue
Author: Shubham Dipt
Author-email: shubham.dipt@gmail.com
License: MIT
Keywords: django,queue,task,manager
Platform: any
Classifier: Programming Language :: Python :: 3.6
Classifier: License :: OSI Approved :: MIT License
Classifier: Operating System :: OS Independent
License-File: LICENSE
Requires-Dist: Django (>=3.0.0)
